{
  "headers": {
    "x-github-request-id": "3D12:37E8:1DC649:223FA5:5FB09A6E",
    "x-cache-hits": "0, 1",
    "vary": "Authorization,Accept-Encoding",
    "strict-transport-security": "max-age=31536000",
    "expires": "Sun, 15 Nov 2020 03:09:40 GMT",
    "x-served-by": "cache-wdc5520-WDC",
    "accept-ranges": "bytes",
    "x-timer": "S1605409481.969046,VS0,VE1",
    "content-type": "text/plain; charset=utf-8",
    "etag": "W/\"6e46469f6500bb57691b75214e87d6a7a56dbb0c48f4369e3c1a368e5aa189bc\"",
    "date": "Sun, 15 Nov 2020 03:04:40 GMT",
    "access-control-allow-origin": "*",
    "cache-control": "max-age=300",
    "content-security-policy": "default-src 'none'; style-src 'unsafe-inline'; sandbox",
    "x-content-type-options": "nosniff",
    "x-xss-protection": "1; mode=block",
    "via": "1.1 varnish (Varnish/6.0), 1.1 varnish",
    "x-fastly-request-id": "2b3b7b12919bb19b94c2cff1edb52811b2b65298",
    "x-frame-options": "deny",
    "connection": "keep-alive",
    "source-age": "90",
    "x-cache": "HFM, HIT"
  },
  "url": "https://raw.githubusercontent.com/matt-mcmahon/functional/next/source/app/functions/reduce.ts"
}