{
  "headers": {
    "etag": "W/\"c466ce488e1bf42a26fb2f1e963ccbc4735d5f19cc290fc82889cd2bf7a6c9ea\"",
    "x-cache": "MISS, HIT",
    "x-cache-hits": "0, 1",
    "x-github-request-id": "3E8E:6B76:55363:69C22:5FB099D4",
    "via": "1.1 varnish (Varnish/6.0), 1.1 varnish",
    "x-content-type-options": "nosniff",
    "accept-ranges": "bytes",
    "source-age": "241",
    "vary": "Authorization,Accept-Encoding",
    "access-control-allow-origin": "*",
    "content-security-policy": "default-src 'none'; style-src 'unsafe-inline'; sandbox",
    "x-timer": "S1605409481.886326,VS0,VE1",
    "content-type": "text/plain; charset=utf-8",
    "x-fastly-request-id": "6d47aea285c73cb9691bbf33a5f1bf54ae799c6c",
    "date": "Sun, 15 Nov 2020 03:04:40 GMT",
    "strict-transport-security": "max-age=31536000",
    "connection": "keep-alive",
    "x-xss-protection": "1; mode=block",
    "expires": "Sun, 15 Nov 2020 03:09:40 GMT",
    "cache-control": "max-age=300",
    "x-frame-options": "deny",
    "x-served-by": "cache-dca17774-DCA"
  },
  "url": "https://raw.githubusercontent.com/matt-mcmahon/functional/next/source/app/functions/join.ts"
}