{
  "headers": {
    "x-amz-request-id": "68E6DB8B9708C92D",
    "content-length": "975",
    "date": "Sun, 15 Nov 2020 18:45:22 GMT",
    "x-amz-version-id": "5eLq2XzT8ZzwJdzGPbzT5TzjOskoEZ3k",
    "report-to": "{\"endpoints\":[{\"url\":\"https:\\/\\/a.nel.cloudflare.com\\/report?s=8OMX9yWWk5Zd0zKrg%2FQVyq%2B3DJz1SFKq1ps08aKZCe5MXfAb6o%2Fp%2B0w76LDPndSlKUwQDafnXCuMgtS%2FzI7S%2BhTdpKJS2SUJXPc%3D\"}],\"group\":\"cf-nel\",\"max_age\":604800}",
    "accept-ranges": "bytes",
    "etag": "\"a116cc07f3c3e00cc9cf3baaf6721cc5\"",
    "cache-control": "public, max-age=31536000, immutable",
    "age": "301852",
    "set-cookie": "__cfduid=d7d0d6a9c76556790ebb0ea1b94b04abb1605465922; expires=Tue, 15-Dec-20 18:45:22 GMT; path=/; domain=.deno.land; HttpOnly; SameSite=Lax; Secure",
    "cf-ray": "5f2b21023f3902f7-IAD",
    "expect-ct": "max-age=604800, report-uri=\"https://report-uri.cloudflare.com/cdn-cgi/beacon/expect-ct\"",
    "cf-cache-status": "HIT",
    "server": "cloudflare",
    "x-amz-id-2": "DAUJ25ahZQNuRKECeFkLXOFXuc4iA9OR8SySP3PMycN3xKI8pw8Jh4pCXemj70nGN3j5jO3yScc=",
    "content-type": "application/typescript; charset=utf-8",
    "vary": "Accept-Encoding",
    "nel": "{\"report_to\":\"cf-nel\",\"max_age\":604800}",
    "cf-request-id": "066ed2f55f000002f732a96000000001",
    "last-modified": "Mon, 09 Nov 2020 00:00:45 GMT",
    "access-control-allow-origin": "*"
  },
  "url": "https://deno.land/std@0.77.0/fs/_util.ts"
}